{"sources":[{"prev_ver":520093697,"name":"RLAudio","uuid":"ab3256da-59e9-430d-9891-f08f5f46d21b","id":"wasapi_process_output_capture","versioned_id":"wasapi_process_output_capture","settings":{"window":"Rocket League (64-bit, DX11, Cooked):LaunchUnrealUWindowsClient:RocketLeague.exe"},"mixers":255,"sync":0,"flags":0,"volume":1.0,"balance":0.5,"enabled":true,"muted":false,"push-to-mute":false,"push-to-mute-delay":0,"push-to-talk":false,"push-to-talk-delay":0,"hotkeys":{"libobs.mute":[],"libobs.unmute":[],"libobs.push-to-mute":[],"libobs.push-to-talk":[]},"deinterlace_mode":0,"deinterlace_field_order":0,"monitoring_type":0,"private_settings":{}},{"prev_ver":520093697,"name":"RLCapture","uuid":"63b96c62-e527-405d-8f9d-1529714cab0f","id":"game_capture","versioned_id":"game_capture","settings":{"window":"Rocket League (64-bit, DX11, Cooked):LaunchUnrealUWindowsClient:RocketLeague.exe","capture_mode":"window"},"mixers":0,"sync":0,"flags":0,"volume":1.0,"balance":0.5,"enabled":true,"muted":false,"push-to-mute":false,"push-to-mute-delay":0,"push-to-talk":false,"push-to-talk-delay":0,"hotkeys":{"libobs.mute":[],"libobs.unmute":[],"libobs.push-to-mute":[],"libobs.push-to-talk":[],"hotkey_start":[],"hotkey_stop":[]},"deinterlace_mode":0,"deinterlace_field_order":0,"monitoring_type":0,"private_settings":{}},{"prev_ver":520093697,"name":"ReplayBlue","uuid":"9ec8d536-e664-4432-8868-de56050f73e1","id":"image_source","versioned_id":"image_source","settings":{"file":"D:/MNVL/Stream/Game/RL/graphics/ReplayBlue.png"},"mixers":0,"sync":0,"flags":0,"volume":1.0,"balance":0.5,"enabled":true,"muted":false,"push-to-mute":false,"push-to-mute-delay":0,"push-to-talk":false,"push-to-talk-delay":0,"hotkeys":{},"deinterlace_mode":0,"deinterlace_field_order":0,"monitoring_type":0,"private_settings":{}},{"prev_ver":520093697,"name":"ReplayOrange","uuid":"60f6434e-9807-4847-a534-c5c4f417aa7a","id":"image_source","versioned_id":"image_source","settings":{"file":"D:/MNVL/Stream/Game/RL/graphics/ReplayOrange.png"},"mixers":0,"sync":0,"flags":0,"volume":1.0,"balance":0.5,"enabled":true,"muted":false,"push-to-mute":false,"push-to-mute-delay":0,"push-to-talk":false,"push-to-talk-delay":0,"hotkeys":{},"deinterlace_mode":0,"deinterlace_field_order":0,"monitoring_type":0,"private_settings":{}},{"prev_ver":520093697,"name":"ReplayAssisterBlue","uuid":"cc5d93b2-8513-4cbe-b672-26d88ca2bb7d","id":"image_source","versioned_id":"image_source","settings":{"file":"D:/MNVL/Stream/Game/RL/graphics/ReplayAssisterBlue.png"},"mixers":0,"sync":0,"flags":0,"volume":1.0,"balance":0.5,"enabled":true,"muted":false,"push-to-mute":false,"push-to-mute-delay":0,"push-to-talk":false,"push-to-talk-delay":0,"hotkeys":{},"deinterlace_mode":0,"deinterlace_field_order":0,"monitoring_type":0,"private_settings":{}},{"prev_ver":520093697,"name":"ReplayAssisterOrange","uuid":"0ff2beda-02f0-4124-873c-ec535c9f6de1","id":"image_source","versioned_id":"image_source","settings":{"file":"D:/MNVL/Stream/Game/RL/graphics/ReplayAssisterOrange.png"},"mixers":0,"sync":0,"flags":0,"volume":1.0,"balance":0.5,"enabled":true,"muted":false,"push-to-mute":false,"push-to-mute-delay":0,"push-to-talk":false,"push-to-talk-delay":0,"hotkeys":{},"deinterlace_mode":0,"deinterlace_field_order":0,"monitoring_type":0,"private_settings":{}},{"prev_ver":520093697,"name":"Scorer","uuid":"1ec01c47-7603-4876-b270-250e82eb352d","id":"text_gdiplus","versioned_id":"text_gdiplus_v2","settings":{"text":"Flow.","font":{"face":"Rift Bold","flags":1,"size":256,"style":"Bold"},"transform":1},"mixers":0,"sync":0,"flags":0,"volume":1.0,"balance":0.5,"enabled":true,"muted":false,"push-to-mute":false,"push-to-mute-delay":0,"push-to-talk":false,"push-to-talk-delay":0,"hotkeys":{},"deinterlace_mode":0,"deinterlace_field_order":0,"monitoring_type":0,"private_settings":{}},{"prev_ver":520093697,"name":"Assister","uuid":"fe57fd55-d9ee-427a-86dc-1ae1f8cf90cf","id":"text_gdiplus","versioned_id":"text_gdiplus_v2","settings":{"text":"no luck 2","font":{"face":"Rift Bold","flags":1,"size":256,"style":"Bold"},"transform":1},"mixers":0,"sync":0,"flags":0,"volume":1.0,"balance":0.5,"enabled":true,"muted":false,"push-to-mute":false,"push-to-mute-delay":0,"push-to-talk":false,"push-to-talk-delay":0,"hotkeys":{},"deinterlace_mode":0,"deinterlace_field_order":0,"monitoring_type":0,"private_settings":{}},{"prev_ver":520093697,"name":"ScoreTimerOL.png","uuid":"ee358a52-7f9d-46f2-8c55-0dcc812e058f","id":"image_source","versioned_id":"image_source","settings":{"file":"D:/MNVL/Stream/Game/RL/graphics/ScoreTimerOL.png"},"mixers":0,"sync":0,"flags":0,"volume":1.0,"balance":0.5,"enabled":true,"muted":false,"push-to-mute":false,"push-to-mute-delay":0,"push-to-talk":false,"push-to-talk-delay":0,"hotkeys":{},"deinterlace_mode":0,"deinterlace_field_order":0,"monitoring_type":0,"private_settings":{}},{"prev_ver":520093697,"name":"Team1Name","uuid":"4c4b9724-9573-4a24-8ea9-e221fd736e14","id":"text_gdiplus","versioned_id":"text_gdiplus_v2","settings":{"text":"Winter","font":{"face":"Rift Bold","flags":1,"size":256,"style":"Bold"},"transform":1},"mixers":0,"sync":0,"flags":0,"volume":1.0,"balance":0.5,"enabled":true,"muted":false,"push-to-mute":false,"push-to-mute-delay":0,"push-to-talk":false,"push-to-talk-delay":0,"hotkeys":{},"deinterlace_mode":0,"deinterlace_field_order":0,"monitoring_type":0,"private_settings":{}},{"prev_ver":520093697,"name":"Team2Name","uuid":"2bfe06f7-599d-403a-8c3e-e66d814e9291","id":"text_gdiplus","versioned_id":"text_gdiplus_v2","settings":{"text":"Fall","undo_sname":"Team2Name","font":{"face":"Rift Bold","flags":1,"size":256,"style":"Bold"},"transform":1},"mixers":0,"sync":0,"flags":0,"volume":1.0,"balance":0.5,"enabled":true,"muted":false,"push-to-mute":false,"push-to-mute-delay":0,"push-to-talk":false,"push-to-talk-delay":0,"hotkeys":{},"deinterlace_mode":0,"deinterlace_field_order":0,"monitoring_type":0,"private_settings":{}},{"prev_ver":520093697,"name":"Score1","uuid":"d319241b-8367-4e71-b081-07e743d56c34","id":"text_gdiplus","versioned_id":"text_gdiplus_v2","settings":{"text":"0","font":{"face":"Rift Bold","flags":1,"size":256,"style":"Bold"},"color":16777215},"mixers":0,"sync":0,"flags":0,"volume":1.0,"balance":0.5,"enabled":true,"muted":false,"push-to-mute":false,"push-to-mute-delay":0,"push-to-talk":false,"push-to-talk-delay":0,"hotkeys":{},"deinterlace_mode":0,"deinterlace_field_order":0,"monitoring_type":0,"private_settings":{}},{"prev_ver":520093697,"name":"Score2","uuid":"54eb6b68-aba2-4204-aa22-2a612a7fa877","id":"text_gdiplus","versioned_id":"text_gdiplus_v2","settings":{"text":"0","font":{"face":"Rift Bold","flags":1,"size":256,"style":"Bold"},"color":16777215},"mixers":0,"sync":0,"flags":0,"volume":1.0,"balance":0.5,"enabled":true,"muted":false,"push-to-mute":false,"push-to-mute-delay":0,"push-to-talk":false,"push-to-talk-delay":0,"hotkeys":{},"deinterlace_mode":0,"deinterlace_field_order":0,"monitoring_type":0,"private_settings":{}},{"prev_ver":520093697,"name":"Timer","uuid":"3451ec52-f526-4339-a63b-abb655a0cc7f","id":"text_gdiplus","versioned_id":"text_gdiplus_v2","settings":{"text":"5:00","font":{"face":"Termina Bold","flags":1,"size":256,"style":"Bold"},"color":16777215},"mixers":0,"sync":0,"flags":0,"volume":1.0,"balance":0.5,"enabled":true,"muted":false,"push-to-mute":false,"push-to-mute-delay":0,"push-to-talk":false,"push-to-talk-delay":0,"hotkeys":{},"deinterlace_mode":0,"deinterlace_field_order":0,"monitoring_type":0,"private_settings":{}},{"prev_ver":520093697,"name":"BlueTicker1","uuid":"66bc20a4-8384-4d5a-bff7-c11df2457da2","id":"image_source","versioned_id":"image_source","settings":{"file":"D:/MNVL/Stream/Game/RL/graphics/BlueTicker.png"},"mixers":0,"sync":0,"flags":0,"volume":1.0,"balance":0.5,"enabled":true,"muted":false,"push-to-mute":false,"push-to-mute-delay":0,"push-to-talk":false,"push-to-talk-delay":0,"hotkeys":{},"deinterlace_mode":0,"deinterlace_field_order":0,"monitoring_type":0,"private_settings":{}},{"prev_ver":520093697,"name":"BlueTicker2","uuid":"21e1b87b-20ca-4a1e-83a5-7f0b5fd33168","id":"image_source","versioned_id":"image_source","settings":{"file":"D:/MNVL/Stream/Game/RL/graphics/BlueTicker.png"},"mixers":0,"sync":0,"flags":0,"volume":1.0,"balance":0.5,"enabled":true,"muted":false,"push-to-mute":false,"push-to-mute-delay":0,"push-to-talk":false,"push-to-talk-delay":0,"hotkeys":{},"deinterlace_mode":0,"deinterlace_field_order":0,"monitoring_type":0,"private_settings":{}},{"prev_ver":520093697,"name":"BlueTicker3","uuid":"6a9e0d6f-f75b-4425-a80b-3a21d37ef0f5","id":"image_source","versioned_id":"image_source","settings":{"file":"D:/MNVL/Stream/Game/RL/graphics/BlueTicker.png"},"mixers":0,"sync":0,"flags":0,"volume":1.0,"balance":0.5,"enabled":true,"muted":false,"push-to-mute":false,"push-to-mute-delay":0,"push-to-talk":false,"push-to-talk-delay":0,"hotkeys":{},"deinterlace_mode":0,"deinterlace_field_order":0,"monitoring_type":0,"private_settings":{}},{"prev_ver":520093697,"name":"OrangeTicker1","uuid":"71df014c-e6d9-420a-9161-ba1ec4c1238e","id":"image_source","versioned_id":"image_source","settings":{"file":"D:/MNVL/Stream/Game/RL/graphics/OrangeTicker.png"},"mixers":0,"sync":0,"flags":0,"volume":1.0,"balance":0.5,"enabled":true,"muted":false,"push-to-mute":false,"push-to-mute-delay":0,"push-to-talk":false,"push-to-talk-delay":0,"hotkeys":{},"deinterlace_mode":0,"deinterlace_field_order":0,"monitoring_type":0,"private_settings":{}},{"prev_ver":520093697,"name":"OrangeTicker2","uuid":"db1ffe17-41f1-471f-872b-6eb71d82b31c","id":"image_source","versioned_id":"image_source","settings":{"file":"D:/MNVL/Stream/Game/RL/graphics/OrangeTicker.png"},"mixers":0,"sync":0,"flags":0,"volume":1.0,"balance":0.5,"enabled":true,"muted":false,"push-to-mute":false,"push-to-mute-delay":0,"push-to-talk":false,"push-to-talk-delay":0,"hotkeys":{},"deinterlace_mode":0,"deinterlace_field_order":0,"monitoring_type":0,"private_settings":{}},{"prev_ver":520093697,"name":"OrangeTicker3","uuid":"699c90b1-b2cc-413c-81d3-61e76985ba2a","id":"image_source","versioned_id":"image_source","settings":{"file":"D:/MNVL/Stream/Game/RL/graphics/OrangeTicker.png"},"mixers":0,"sync":0,"flags":0,"volume":1.0,"balance":0.5,"enabled":true,"muted":false,"push-to-mute":false,"push-to-mute-delay":0,"push-to-talk":false,"push-to-talk-delay":0,"hotkeys":{},"deinterlace_mode":0,"deinterlace_field_order":0,"monitoring_type":0,"private_settings":{}},{"prev_ver":520093697,"name":"TickersNS","uuid":"4b0d2414-f3bf-4a07-ad63-cec255ecde4d","id":"scene","versioned_id":"scene","settings":{"custom_size":false,"id_counter":10,"items":[{"name":"BlueTicker1","source_uuid":"66bc20a4-8384-4d5a-bff7-c11df2457da2","visible":true,"locked":false,"rot":0.0,"scale_ref":{"x":1920.0,"y":1080.0},"align":5,"bounds_type":0,"bounds_align":0,"bounds_crop":false,"crop_left":0,"crop_top":0,"crop_right":0,"crop_bottom":0,"id":1,"group_item_backup":false,"pos":{"x":797.0,"y":89.0},"scale":{"x":0.24166665971279144,"y":0.24137930572032928},"bounds":{"x":1.0,"y":1.0},"scale_filter":"disable","blend_method":"default","blend_type":"normal","show_transition":{"duration":0},"hide_transition":{"duration":0},"private_settings":{}},{"name":"BlueTicker2","source_uuid":"21e1b87b-20ca-4a1e-83a5-7f0b5fd33168","visible":true,"locked":false,"rot":0.0,"scale_ref":{"x":1920.0,"y":1080.0},"align":5,"bounds_type":0,"bounds_align":0,"bounds_crop":false,"crop_left":0,"crop_top":0,"crop_right":0,"crop_bottom":0,"id":2,"group_item_backup":false,"pos":{"x":716.0,"y":89.0},"scale":{"x":0.24166665971279144,"y":0.24137930572032928},"bounds":{"x":0.0,"y":0.0},"scale_filter":"disable","blend_method":"default","blend_type":"normal","show_transition":{"duration":0},"hide_transition":{"duration":0},"private_settings":{}},{"name":"BlueTicker3","source_uuid":"6a9e0d6f-f75b-4425-a80b-3a21d37ef0f5","visible":false,"locked":false,"rot":0.0,"scale_ref":{"x":1920.0,"y":1080.0},"align":5,"bounds_type":0,"bounds_align":0,"bounds_crop":false,"crop_left":0,"crop_top":0,"crop_right":0,"crop_bottom":0,"id":3,"group_item_backup":false,"pos":{"x":639.0,"y":89.0},"scale":{"x":0.24166665971279144,"y":0.24137930572032928},"bounds":{"x":1.0,"y":1.0},"scale_filter":"disable","blend_method":"default","blend_type":"normal","show_transition":{"duration":0},"hide_transition":{"duration":0},"private_settings":{}},{"name":"OrangeTicker1","source_uuid":"71df014c-e6d9-420a-9161-ba1ec4c1238e","visible":true,"locked":false,"rot":0.0,"scale_ref":{"x":1920.0,"y":1080.0},"align":5,"bounds_type":0,"bounds_align":0,"bounds_crop":false,"crop_left":0,"crop_top":0,"crop_right":0,"crop_bottom":0,"id":5,"group_item_backup":false,"pos":{"x":1065.0,"y":91.0},"scale":{"x":0.24166665971279144,"y":0.24137930572032928},"bounds":{"x":0.0,"y":0.0},"scale_filter":"disable","blend_method":"default","blend_type":"normal","show_transition":{"duration":0},"hide_transition":{"duration":0},"private_settings":{}},{"name":"OrangeTicker2","source_uuid":"db1ffe17-41f1-471f-872b-6eb71d82b31c","visible":true,"locked":false,"rot":0.0,"scale_ref":{"x":1920.0,"y":1080.0},"align":5,"bounds_type":0,"bounds_align":0,"bounds_crop":false,"crop_left":0,"crop_top":0,"crop_right":0,"crop_bottom":0,"id":6,"group_item_backup":false,"pos":{"x":1146.0,"y":91.0},"scale":{"x":0.24166665971279144,"y":0.24137930572032928},"bounds":{"x":0.0,"y":0.0},"scale_filter":"disable","blend_method":"default","blend_type":"normal","show_transition":{"duration":0},"hide_transition":{"duration":0},"private_settings":{}},{"name":"OrangeTicker3","source_uuid":"699c90b1-b2cc-413c-81d3-61e76985ba2a","visible":true,"locked":false,"rot":0.0,"scale_ref":{"x":1920.0,"y":1080.0},"align":5,"bounds_type":0,"bounds_align":0,"bounds_crop":false,"crop_left":0,"crop_top":0,"crop_right":0,"crop_bottom":0,"id":7,"group_item_backup":false,"pos":{"x":1224.0,"y":91.0},"scale":{"x":0.24166665971279144,"y":0.24137930572032928},"bounds":{"x":0.0,"y":0.0},"scale_filter":"disable","blend_method":"default","blend_type":"normal","show_transition":{"duration":0},"hide_transition":{"duration":0},"private_settings":{}}]},"mixers":0,"sync":0,"flags":0,"volume":1.0,"balance":0.5,"enabled":true,"muted":false,"push-to-mute":false,"push-to-mute-delay":0,"push-to-talk":false,"push-to-talk-delay":0,"hotkeys":{"OBSBasic.SelectScene":[],"libobs.show_scene_item.1":[],"libobs.hide_scene_item.1":[],"libobs.show_scene_item.2":[],"libobs.hide_scene_item.2":[],"libobs.show_scene_item.3":[],"libobs.hide_scene_item.3":[],"libobs.show_scene_item.5":[],"libobs.hide_scene_item.5":[],"libobs.show_scene_item.6":[],"libobs.hide_scene_item.6":[],"libobs.show_scene_item.7":[],"libobs.hide_scene_item.7":[]},"deinterlace_mode":0,"deinterlace_field_order":0,"monitoring_type":0,"private_settings":{}},{"prev_ver":520093697,"name":"ScoreNS","uuid":"e6147bd3-e1a1-4b8a-ad60-787c428b00d5","id":"scene","versioned_id":"scene","settings":{"custom_size":false,"id_counter":24,"items":[{"name":"ScoreTimerOL.png","source_uuid":"ee358a52-7f9d-46f2-8c55-0dcc812e058f","visible":true,"locked":true,"rot":0.0,"scale_ref":{"x":1920.0,"y":1080.0},"align":5,"bounds_type":0,"bounds_align":0,"bounds_crop":false,"crop_left":0,"crop_top":0,"crop_right":0,"crop_bottom":0,"id":1,"group_item_backup":false,"pos":{"x":463.0,"y":17.0},"scale":{"x":0.23992276191711426,"y":0.24067796766757965},"bounds":{"x":0.0,"y":0.0},"scale_filter":"disable","blend_method":"default","blend_type":"normal","show_transition":{"duration":0},"hide_transition":{"duration":0},"private_settings":{}},{"name":"Team1Name","source_uuid":"4c4b9724-9573-4a24-8ea9-e221fd736e14","visible":true,"locked":false,"rot":0.0,"scale_ref":{"x":1920.0,"y":1080.0},"align":0,"bounds_type":6,"bounds_align":0,"bounds_crop":false,"crop_left":0,"crop_top":0,"crop_right":0,"crop_bottom":0,"id":2,"group_item_backup":false,"pos":{"x":703.0,"y":55.0},"scale":{"x":0.41737276315689087,"y":0.41796875},"bounds":{"x":303.0,"y":48.0},"scale_filter":"disable","blend_method":"default","blend_type":"normal","show_transition":{"duration":0},"hide_transition":{"duration":0},"private_settings":{}},{"name":"Team2Name","source_uuid":"2bfe06f7-599d-403a-8c3e-e66d814e9291","visible":true,"locked":false,"rot":0.0,"scale_ref":{"x":1920.0,"y":1080.0},"align":0,"bounds_type":6,"bounds_align":0,"bounds_crop":false,"crop_left":0,"crop_top":0,"crop_right":0,"crop_bottom":0,"id":4,"group_item_backup":false,"pos":{"x":1212.0,"y":56.0},"scale":{"x":0.41737276315689087,"y":0.41796875},"bounds":{"x":303.0,"y":48.0},"scale_filter":"disable","blend_method":"default","blend_type":"normal","show_transition":{"duration":0},"hide_transition":{"duration":0},"private_settings":{}},{"name":"Score1","source_uuid":"d319241b-8367-4e71-b081-07e743d56c34","visible":true,"locked":false,"rot":0.0,"scale_ref":{"x":1920.0,"y":1080.0},"align":5,"bounds_type":6,"bounds_align":0,"bounds_crop":false,"crop_left":0,"crop_top":0,"crop_right":0,"crop_bottom":0,"id":5,"group_item_backup":false,"pos":{"x":487.0,"y":22.0},"scale":{"x":0.32031345367431641,"y":0.3203125},"bounds":{"x":46.0,"y":61.0},"scale_filter":"disable","blend_method":"default","blend_type":"normal","show_transition":{"duration":0},"hide_transition":{"duration":0},"private_settings":{}},{"name":"Score2","source_uuid":"54eb6b68-aba2-4204-aa22-2a612a7fa877","visible":true,"locked":false,"rot":0.0,"scale_ref":{"x":1920.0,"y":1080.0},"align":5,"bounds_type":6,"bounds_align":0,"bounds_crop":false,"crop_left":0,"crop_top":0,"crop_right":0,"crop_bottom":0,"id":6,"group_item_backup":false,"pos":{"x":1388.0,"y":22.0},"scale":{"x":0.32031276822090149,"y":0.3203125},"bounds":{"x":46.0,"y":61.0},"scale_filter":"disable","blend_method":"default","blend_type":"normal","show_transition":{"duration":0},"hide_transition":{"duration":0},"private_settings":{}},{"name":"Timer","source_uuid":"3451ec52-f526-4339-a63b-abb655a0cc7f","visible":true,"locked":false,"rot":0.0,"scale_ref":{"x":1920.0,"y":1080.0},"align":5,"bounds_type":6,"bounds_align":0,"bounds_crop":false,"crop_left":0,"crop_top":0,"crop_right":0,"crop_bottom":0,"id":8,"group_item_backup":false,"pos":{"x":891.0,"y":41.0},"scale":{"x":0.3203125,"y":0.3203125},"bounds":{"x":140.0,"y":40.0},"scale_filter":"disable","blend_method":"default","blend_type":"normal","show_transition":{"duration":0},"hide_transition":{"duration":0},"private_settings":{}},{"name":"TickersNS","source_uuid":"4b0d2414-f3bf-4a07-ad63-cec255ecde4d","visible":true,"locked":false,"rot":0.0,"scale_ref":{"x":1920.0,"y":1080.0},"align":5,"bounds_type":0,"bounds_align":0,"bounds_crop":false,"crop_left":0,"crop_top":0,"crop_right":0,"crop_bottom":0,"id":23,"group_item_backup":false,"pos":{"x":0.0,"y":-2.0},"scale":{"x":1.0,"y":1.0},"bounds":{"x":1.0,"y":1.0},"scale_filter":"disable","blend_method":"default","blend_type":"normal","show_transition":{"duration":0},"hide_transition":{"duration":0},"private_settings":{}}]},"mixers":0,"sync":0,"flags":0,"volume":1.0,"balance":0.5,"enabled":true,"muted":false,"push-to-mute":false,"push-to-mute-delay":0,"push-to-talk":false,"push-to-talk-delay":0,"hotkeys":{"OBSBasic.SelectScene":[],"libobs.show_scene_item.1":[],"libobs.hide_scene_item.1":[],"libobs.show_scene_item.2":[],"libobs.hide_scene_item.2":[],"libobs.show_scene_item.4":[],"libobs.hide_scene_item.4":[],"libobs.show_scene_item.5":[],"libobs.hide_scene_item.5":[],"libobs.show_scene_item.6":[],"libobs.hide_scene_item.6":[],"libobs.show_scene_item.8":[],"libobs.hide_scene_item.8":[],"libobs.show_scene_item.23":[],"libobs.hide_scene_item.23":[]},"deinterlace_mode":0,"deinterlace_field_order":0,"monitoring_type":0,"private_settings":{}},{"prev_ver":520093697,"name":"Replay","uuid":"984ef1b1-06e1-4c84-b301-6042ecbf67e8","id":"scene","versioned_id":"scene","settings":{"custom_size":false,"id_counter":12,"items":[{"name":"RLAudio","source_uuid":"ab3256da-59e9-430d-9891-f08f5f46d21b","visible":true,"locked":false,"rot":0.0,"scale_ref":{"x":1920.0,"y":1080.0},"align":5,"bounds_type":0,"bounds_align":0,"bounds_crop":false,"crop_left":0,"crop_top":0,"crop_right":0,"crop_bottom":0,"id":12,"group_item_backup":false,"pos":{"x":0.0,"y":0.0},"scale":{"x":1.0,"y":1.0},"bounds":{"x":0.0,"y":0.0},"scale_filter":"disable","blend_method":"default","blend_type":"normal","show_transition":{"duration":0},"hide_transition":{"duration":0},"private_settings":{}},{"name":"RLCapture","source_uuid":"63b96c62-e527-405d-8f9d-1529714cab0f","visible":true,"locked":false,"rot":0.0,"scale_ref":{"x":1920.0,"y":1080.0},"align":5,"bounds_type":2,"bounds_align":0,"bounds_crop":false,"crop_left":0,"crop_top":0,"crop_right":0,"crop_bottom":0,"id":1,"group_item_backup":false,"pos":{"x":0.0,"y":0.0},"scale":{"x":1.0,"y":1.0},"bounds":{"x":1920.0,"y":1080.0},"scale_filter":"disable","blend_method":"default","blend_type":"normal","show_transition":{"duration":0},"hide_transition":{"duration":0},"private_settings":{}},{"name":"ReplayBlue","source_uuid":"9ec8d536-e664-4432-8868-de56050f73e1","visible":false,"locked":false,"rot":0.0,"scale_ref":{"x":1920.0,"y":1080.0},"align":5,"bounds_type":0,"bounds_align":0,"bounds_crop":false,"crop_left":0,"crop_top":0,"crop_right":0,"crop_bottom":0,"id":3,"group_item_backup":false,"pos":{"x":836.0,"y":924.0},"scale":{"x":0.37310194969177246,"y":0.37417218089103699},"bounds":{"x":0.0,"y":0.0},"scale_filter":"disable","blend_method":"default","blend_type":"normal","show_transition":{"duration":0},"hide_transition":{"duration":0},"private_settings":{}},{"name":"ReplayOrange","source_uuid":"60f6434e-9807-4847-a534-c5c4f417aa7a","visible":true,"locked":false,"rot":0.0,"scale_ref":{"x":1920.0,"y":1080.0},"align":5,"bounds_type":0,"bounds_align":0,"bounds_crop":false,"crop_left":0,"crop_top":0,"crop_right":0,"crop_bottom":0,"id":4,"group_item_backup":false,"pos":{"x":836.0,"y":924.0},"scale":{"x":0.37310194969177246,"y":0.37417218089103699},"bounds":{"x":0.0,"y":0.0},"scale_filter":"disable","blend_method":"default","blend_type":"normal","show_transition":{"duration":0},"hide_transition":{"duration":0},"private_settings":{}},{"name":"ReplayAssisterBlue","source_uuid":"cc5d93b2-8513-4cbe-b672-26d88ca2bb7d","visible":false,"locked":false,"rot":0.0,"scale_ref":{"x":1920.0,"y":1080.0},"align":5,"bounds_type":0,"bounds_align":0,"bounds_crop":false,"crop_left":0,"crop_top":0,"crop_right":0,"crop_bottom":0,"id":5,"group_item_backup":false,"pos":{"x":836.0,"y":924.0},"scale":{"x":0.37310194969177246,"y":0.37417218089103699},"bounds":{"x":0.0,"y":0.0},"scale_filter":"disable","blend_method":"default","blend_type":"normal","show_transition":{"duration":0},"hide_transition":{"duration":0},"private_settings":{}},{"name":"ReplayAssisterOrange","source_uuid":"0ff2beda-02f0-4124-873c-ec535c9f6de1","visible":true,"locked":false,"rot":0.0,"scale_ref":{"x":1920.0,"y":1080.0},"align":5,"bounds_type":0,"bounds_align":0,"bounds_crop":false,"crop_left":0,"crop_top":0,"crop_right":0,"crop_bottom":0,"id":6,"group_item_backup":false,"pos":{"x":836.0,"y":924.0},"scale":{"x":0.37310194969177246,"y":0.37417218089103699},"bounds":{"x":0.0,"y":0.0},"scale_filter":"disable","blend_method":"default","blend_type":"normal","show_transition":{"duration":0},"hide_transition":{"duration":0},"private_settings":{}},{"name":"Scorer","source_uuid":"1ec01c47-7603-4876-b270-250e82eb352d","visible":true,"locked":false,"rot":0.0,"scale_ref":{"x":1920.0,"y":1080.0},"align":1,"bounds_type":6,"bounds_align":1,"bounds_crop":false,"crop_left":0,"crop_top":0,"crop_right":0,"crop_bottom":0,"id":2,"group_item_backup":false,"pos":{"x":868.0,"y":955.0},"scale":{"x":0.53340756893157959,"y":0.53515625},"bounds":{"x":163.0,"y":39.0},"scale_filter":"disable","blend_method":"default","blend_type":"normal","show_transition":{"duration":0},"hide_transition":{"duration":0},"private_settings":{}},{"name":"Assister","source_uuid":"fe57fd55-d9ee-427a-86dc-1ae1f8cf90cf","visible":true,"locked":false,"rot":0.0,"scale_ref":{"x":1920.0,"y":1080.0},"align":1,"bounds_type":6,"bounds_align":1,"bounds_crop":false,"crop_left":0,"crop_top":0,"crop_right":0,"crop_bottom":0,"id":7,"group_item_backup":false,"pos":{"x":868.0,"y":1014.0},"scale":{"x":0.40611815452575684,"y":0.40530312061309814},"bounds":{"x":183.0,"y":27.0},"scale_filter":"disable","blend_method":"default","blend_type":"normal","show_transition":{"duration":0},"hide_transition":{"duration":0},"private_settings":{}},{"name":"ScoreNS","source_uuid":"e6147bd3-e1a1-4b8a-ad60-787c428b00d5","visible":true,"locked":false,"rot":0.0,"scale_ref":{"x":1920.0,"y":1080.0},"align":5,"bounds_type":0,"bounds_align":0,"bounds_crop":false,"crop_left":0,"crop_top":0,"crop_right":0,"crop_bottom":0,"id":10,"group_item_backup":false,"pos":{"x":0.0,"y":0.0},"scale":{"x":1.0,"y":1.0},"bounds":{"x":0.0,"y":0.0},"scale_filter":"disable","blend_method":"default","blend_type":"normal","show_transition":{"duration":0},"hide_transition":{"duration":0},"private_settings":{}}]},"mixers":0,"sync":0,"flags":0,"volume":1.0,"balance":0.5,"enabled":true,"muted":false,"push-to-mute":false,"push-to-mute-delay":0,"push-to-talk":false,"push-to-talk-delay":0,"hotkeys":{"OBSBasic.SelectScene":[],"libobs.show_scene_item.12":[],"libobs.hide_scene_item.12":[],"libobs.show_scene_item.1":[],"libobs.hide_scene_item.1":[],"libobs.show_scene_item.3":[],"libobs.hide_scene_item.3":[],"libobs.show_scene_item.4":[],"libobs.hide_scene_item.4":[],"libobs.show_scene_item.5":[],"libobs.hide_scene_item.5":[],"libobs.show_scene_item.6":[],"libobs.hide_scene_item.6":[],"libobs.show_scene_item.2":[],"libobs.hide_scene_item.2":[],"libobs.show_scene_item.7":[],"libobs.hide_scene_item.7":[],"libobs.show_scene_item.10":[],"libobs.hide_scene_item.10":[]},"deinterlace_mode":0,"deinterlace_field_order":0,"monitoring_type":0,"private_settings":{}}]}